doehyunbaek/__init__.py
doehyunbaek/anon_to_zenodo.py
doehyunbaek/devc_to_docker.py
doehyunbaek/main.py
doehyunbaek-0.2.0.dist-info/METADATA
doehyunbaek-0.2.0.dist-info/WHEEL
doehyunbaek-0.2.0.dist-info/entry_points.txt
doehyunbaek-0.2.0.dist-info/RECORD
