Metadata-Version: 2.4
Name: doehyunbaek
Version: 0.2.0
Summary: Personal utilities
Requires-Python: >=3.10
Requires-Dist: pystow
Requires-Dist: zenodo-client
